nix_shell_utils/__init__.py
nix_shell_utils-0.0.12.dist-info/LICENSE
nix_shell_utils-0.0.12.dist-info/METADATA
nix_shell_utils-0.0.12.dist-info/WHEEL
nix_shell_utils-0.0.12.dist-info/top_level.txt
nix_shell_utils-0.0.12.dist-info/RECORD
