Metadata-Version: 2.1
Name: nix-shell-utils
Version: 0.0.12
Summary: Python wrapper functions for common shell commands
Author: Alberto Garcia Izquierdo
Project-URL: repository, https://github.com/alb-garcia/nix_shell_utils
Project-URL: home, https://github.com/alb-garcia/nix_shell_utils
Project-URL: documentation, https://nix-shell-utils.readthedocs.io
Classifier: Programming Language :: Python :: 3
Classifier: License :: OSI Approved :: MIT License
Requires-Python: >=3.7
License-File: LICENSE
Requires-Dist: setuptools (>64.0)
